{
	"election_results":{
		"Alabama":{
			"contests":{
				"presidential":{
					"winners":1,
					"candidates":[
						"Biden",
						"Trump"
					],
					"results":[849624,1441170],
					"ballots_cast":2323282,
					"state_id":1,
					"margin":-0.2582274967
				}
			},
			"round_sizes_Minerva_EoR":[114,213],
			"round_sizes_Minerva_EoR_scaled":[116,217],
			"round_sizes_factor":1.868421053,
			"distinct_Minerva_EoR":[116,217],
			"distinct_factor":1.870689655,
			"stop_prob_Minerva":0.9181868455,
			"stop_prob_EoR":0.9104180435
		},
		"Alaska":{
			"contests":{
				"presidential":{
					"winners":1,
					"candidates":[
						"Biden",
						"Trump"
					],
					"results":[153778,189951],
					"ballots_cast":359530,
					"state_id":2,
					"margin":-0.1052369745
				}
			},
			"round_sizes_Minerva_EoR":[639,1301],
			"round_sizes_Minerva_EoR_scaled":[669,1361],
			"round_sizes_factor":2.03599374,
			"distinct_Minerva_EoR":[669,1359],
			"distinct_factor":2.031390135,
			"stop_prob_Minerva":0.9068564772,
			"stop_prob_EoR":0.9044397413
		},
		"Arizona":{
			"contests":{
				"presidential":{
					"winners":1,
					"candidates":[
						"Biden",
						"Trump"
					],
					"results":[1672143,1661686],
					"ballots_cast":3387326,
					"state_id":4,
					"margin":0.003136633583
				}
			},
			"round_sizes_Minerva_EoR":[698936,1453108],
			"round_sizes_Minerva_EoR_scaled":[710152,1476426],
			"round_sizes_factor":2.079028695,
			"distinct_Minerva_EoR":[640652,1196732],
			"distinct_factor":1.867990734,
			"stop_prob_EoR":0.899858637
		},
		"Arkansas":{
			"contests":{
				"presidential":{
					"winners":1,
					"candidates":[
						"Biden",
						"Trump"
					],
					"results":[423932,760647],
					"ballots_cast":1219069,
					"state_id":5,
					"margin":-0.2842486656
				}
			},
			"round_sizes_Minerva_EoR":[88,176],
			"round_sizes_Minerva_EoR_scaled":[91,182],
			"round_sizes_factor":2,
			"distinct_Minerva_EoR":[91,182],
			"distinct_factor":2,
			"stop_prob_Minerva":0.9080621452,
			"stop_prob_EoR":0.9088256432
		},
		"California":{
			"contests":{
				"presidential":{
					"winners":1,
					"candidates":[
						"Biden",
						"Trump"
					],
					"results":[11110250,6006429],
					"ballots_cast":17500881,
					"state_id":6,
					"margin":0.2981782272
				}
			},
			"round_sizes_Minerva_EoR":[79,160],
			"round_sizes_Minerva_EoR_scaled":[81,164],
			"round_sizes_factor":2.025316456,
			"distinct_Minerva_EoR":[81,164],
			"distinct_factor":2.024691358,
			"stop_prob_Minerva":0.9121085803,
			"stop_prob_EoR":0.9157899539
		},
		"Colorado":{
			"contests":{
				"presidential":{
					"winners":1,
					"candidates":[
						"Biden",
						"Trump"
					],
					"results":[1804352,1364607],
					"ballots_cast":3279980,
					"state_id":8,
					"margin":0.1387663898
				}
			},
			"round_sizes_Minerva_EoR":[371,747],
			"round_sizes_Minerva_EoR_scaled":[384,774],
			"round_sizes_factor":2.013477089,
			"distinct_Minerva_EoR":[384,774],
			"distinct_factor":2.015625,
			"stop_prob_Minerva":0.9089399888,
			"stop_prob_EoR":0.9059606447
		},
		"Connecticut":{
			"contests":{
				"presidential":{
					"winners":1,
					"candidates":[
						"Biden",
						"Trump"
					],
					"results":[1080831,714717],
					"ballots_cast":1823857,
					"state_id":9,
					"margin":0.2039009818
				}
			},
			"round_sizes_Minerva_EoR":[171,345],
			"round_sizes_Minerva_EoR_scaled":[174,351],
			"round_sizes_factor":2.01754386,
			"distinct_Minerva_EoR":[174,351],
			"distinct_factor":2.017241379,
			"stop_prob_Minerva":0.9056107604,
			"stop_prob_EoR":0.9092601862
		},
		"Delaware":{
			"contests":{
				"presidential":{
					"winners":1,
					"candidates":[
						"Biden",
						"Trump"
					],
					"results":[296268,200603],
					"ballots_cast":504346,
					"state_id":10,
					"margin":0.1925348833
				}
			},
			"round_sizes_Minerva_EoR":[196,381],
			"round_sizes_Minerva_EoR_scaled":[199,387],
			"round_sizes_factor":1.943877551,
			"distinct_Minerva_EoR":[199,387],
			"distinct_factor":1.944723618,
			"stop_prob_Minerva":0.9131529252,
			"stop_prob_EoR":0.9068367191
		},
		"DistrictOfColumbia":{
			"contests":{
				"presidential":{
					"winners":1,
					"candidates":[
						"Biden",
						"Trump"
					],
					"results":[317323,18586],
					"ballots_cast":344356,
					"state_id":11,
					"margin":0.889339077
				}
			},
			"round_sizes_Minerva_EoR":[7,13],
			"round_sizes_Minerva_EoR_scaled":[8,14],
			"round_sizes_factor":1.857142857,
			"distinct_Minerva_EoR":[8,14],
			"distinct_factor":1.75,
			"stop_prob_Minerva":0.9466252303,
			"stop_prob_EoR":0.9681072518
		},
		"Florida":{
			"contests":{
				"presidential":{
					"winners":1,
					"candidates":[
						"Biden",
						"Trump"
					],
					"results":[5297045,5668731],
					"ballots_cast":11067456,
					"state_id":12,
					"margin":-0.03389509324
				}
			},
			"round_sizes_Minerva_EoR":[6015,12421],
			"round_sizes_Minerva_EoR_scaled":[6071,12537],
			"round_sizes_factor":2.065004156,
			"distinct_Minerva_EoR":[6070,12530],
			"distinct_factor":2.064250412,
			"stop_prob_Minerva":0.9012104325,
			"stop_prob_EoR":0.9004058841
		},
		"Georgia":{
			"contests":{
				"presidential":{
					"winners":1,
					"candidates":[
						"Biden",
						"Trump"
					],
					"results":[2473633,2461854],
					"ballots_cast":4999960,
					"state_id":13,
					"margin":0.002386593258
				}
			},
			"round_sizes_Minerva_EoR":[1207283,2509975],
			"round_sizes_Minerva_EoR_scaled":[1223054,2542764],
			"round_sizes_factor":2.079027867,
			"distinct_Minerva_EoR":[1084953,1993171],
			"distinct_factor":1.837103543,
			"stop_prob_EoR":0.8998831702
		},
		"Hawaii":{
			"contests":{
				"presidential":{
					"winners":1,
					"candidates":[
						"Biden",
						"Trump"
					],
					"results":[366130,196864],
					"ballots_cast":579784,
					"state_id":15,
					"margin":0.3006532929
				}
			},
			"round_sizes_Minerva_EoR":[79,158],
			"round_sizes_Minerva_EoR_scaled":[82,163],
			"round_sizes_factor":2,
			"distinct_Minerva_EoR":[82,163],
			"distinct_factor":1.987804878,
			"stop_prob_Minerva":0.9157917518,
			"stop_prob_EoR":0.9146696889
		},
		"Idaho":{
			"contests":{
				"presidential":{
					"winners":1,
					"candidates":[
						"Biden",
						"Trump"
					],
					"results":[287021,554119],
					"ballots_cast":868014,
					"state_id":16,
					"margin":-0.3175428585
				}
			},
			"round_sizes_Minerva_EoR":[75,140],
			"round_sizes_Minerva_EoR_scaled":[78,145],
			"round_sizes_factor":1.866666667,
			"distinct_Minerva_EoR":[78,145],
			"distinct_factor":1.858974359,
			"stop_prob_Minerva":0.9232808175,
			"stop_prob_EoR":0.9146903202
		},
		"Illinois":{
			"contests":{
				"presidential":{
					"winners":1,
					"candidates":[
						"Biden",
						"Trump"
					],
					"results":[3471915,2446891],
					"ballots_cast":6033743,
					"state_id":17,
					"margin":0.1731808747
				}
			},
			"round_sizes_Minerva_EoR":[240,473],
			"round_sizes_Minerva_EoR_scaled":[245,483],
			"round_sizes_factor":1.970833333,
			"distinct_Minerva_EoR":[245,483],
			"distinct_factor":1.971428571,
			"stop_prob_Minerva":0.9106993321,
			"stop_prob_EoR":0.9034578497
		},
		"Indiana":{
			"contests":{
				"presidential":{
					"winners":1,
					"candidates":[
						"Biden",
						"Trump"
					],
					"results":[1242416,1729519],
					"ballots_cast":3033118,
					"state_id":18,
					"margin":-0.1639009601
				}
			},
			"round_sizes_Minerva_EoR":[267,537],
			"round_sizes_Minerva_EoR_scaled":[273,549],
			"round_sizes_factor":2.011235955,
			"distinct_Minerva_EoR":[273,549],
			"distinct_factor":2.010989011,
			"stop_prob_Minerva":0.9111136542,
			"stop_prob_EoR":0.9051436721
		},
		"Iowa":{
			"contests":{
				"presidential":{
					"winners":1,
					"candidates":[
						"Biden",
						"Trump"
					],
					"results":[759061,897672],
					"ballots_cast":1700130,
					"state_id":19,
					"margin":-0.08366526169
				}
			},
			"round_sizes_Minerva_EoR":[1010,2031],
			"round_sizes_Minerva_EoR_scaled":[1037,2085],
			"round_sizes_factor":2.010891089,
			"distinct_Minerva_EoR":[1037,2084],
			"distinct_factor":2.009643202,
			"stop_prob_Minerva":0.904891218,
			"stop_prob_EoR":0.9013786559
		},
		"Kansas":{
			"contests":{
				"presidential":{
					"winners":1,
					"candidates":[
						"Biden",
						"Trump"
					],
					"results":[570323,771406],
					"ballots_cast":1372303,
					"state_id":20,
					"margin":-0.1498685651
				}
			},
			"round_sizes_Minerva_EoR":[313,629],
			"round_sizes_Minerva_EoR_scaled":[321,644],
			"round_sizes_factor":2.009584665,
			"distinct_Minerva_EoR":[321,644],
			"distinct_factor":2.00623053,
			"stop_prob_Minerva":0.9045484262,
			"stop_prob_EoR":0.9032024227
		},
		"Kentucky":{
			"contests":{
				"presidential":{
					"winners":1,
					"candidates":[
						"Biden",
						"Trump"
					],
					"results":[772474,1326646],
					"ballots_cast":2136768,
					"state_id":21,
					"margin":-0.264002058
				}
			},
			"round_sizes_Minerva_EoR":[103,200],
			"round_sizes_Minerva_EoR_scaled":[105,204],
			"round_sizes_factor":1.941747573,
			"distinct_Minerva_EoR":[105,204],
			"distinct_factor":1.942857143,
			"stop_prob_Minerva":0.910126417,
			"stop_prob_EoR":0.9033667088
		},
		"Louisiana":{
			"contests":{
				"presidential":{
					"winners":1,
					"candidates":[
						"Biden",
						"Trump"
					],
					"results":[856034,1255776],
					"ballots_cast":2148062,
					"state_id":22,
					"margin":-0.1892888091
				}
			},
			"round_sizes_Minerva_EoR":[196,403],
			"round_sizes_Minerva_EoR_scaled":[200,410],
			"round_sizes_factor":2.056122449,
			"distinct_Minerva_EoR":[200,410],
			"distinct_factor":2.05,
			"stop_prob_Minerva":0.9055469194,
			"stop_prob_EoR":0.9084284243
		},
		"Maine":{
			"contests":{
				"presidential":{
					"winners":1,
					"candidates":[
						"Biden",
						"Trump"
					],
					"results":[435072,360737],
					"ballots_cast":828305,
					"state_id":23,
					"margin":0.09340809164
				}
			},
			"round_sizes_Minerva_EoR":[820,1640],
			"round_sizes_Minerva_EoR_scaled":[854,1707],
			"round_sizes_factor":2,
			"distinct_Minerva_EoR":[854,1706],
			"distinct_factor":1.99765808,
			"stop_prob_Minerva":0.9062353237,
			"stop_prob_EoR":0.902151112
		},
		"Maryland":{
			"contests":{
				"presidential":{
					"winners":1,
					"candidates":[
						"Biden",
						"Trump"
					],
					"results":[1985023,976414],
					"ballots_cast":3037030,
					"state_id":24,
					"margin":0.3405809409
				}
			},
			"round_sizes_Minerva_EoR":[64,115],
			"round_sizes_Minerva_EoR_scaled":[66,118],
			"round_sizes_factor":1.796875,
			"distinct_Minerva_EoR":[66,118],
			"distinct_factor":1.787878788,
			"stop_prob_Minerva":0.9225519917,
			"stop_prob_EoR":0.9030393825
		},
		"Massachusetts":{
			"contests":{
				"presidential":{
					"winners":1,
					"candidates":[
						"Biden",
						"Trump"
					],
					"results":[2382202,1167202],
					"ballots_cast":3658005,
					"state_id":25,
					"margin":0.3423109908
				}
			},
			"round_sizes_Minerva_EoR":[64,115],
			"round_sizes_Minerva_EoR_scaled":[66,119],
			"round_sizes_factor":1.796875,
			"distinct_Minerva_EoR":[66,119],
			"distinct_factor":1.803030303,
			"stop_prob_Minerva":0.9247136537,
			"stop_prob_EoR":0.9064348034
		},
		"Michigan":{
			"contests":{
				"presidential":{
					"winners":1,
					"candidates":[
						"Biden",
						"Trump"
					],
					"results":[2804040,2649852],
					"ballots_cast":5539302,
					"state_id":26,
					"margin":0.02827118689
				}
			},
			"round_sizes_Minerva_EoR":[8678,17909],
			"round_sizes_Minerva_EoR_scaled":[8814,18190],
			"round_sizes_factor":2.06372436,
			"distinct_Minerva_EoR":[8807,18161],
			"distinct_factor":2.062109685,
			"stop_prob_Minerva":0.9018635551,
			"stop_prob_EoR":0.9011347338
		},
		"Minnesota":{
			"contests":{
				"presidential":{
					"winners":1,
					"candidates":[
						"Biden",
						"Trump"
					],
					"results":[1717077,1484065],
					"ballots_cast":3277171,
					"state_id":27,
					"margin":0.07279027297
				}
			},
			"round_sizes_Minerva_EoR":[1318,2715],
			"round_sizes_Minerva_EoR_scaled":[1350,2780],
			"round_sizes_factor":2.059939302,
			"distinct_Minerva_EoR":[1350,2779],
			"distinct_factor":2.058518519,
			"stop_prob_Minerva":0.9025009436,
			"stop_prob_EoR":0.9033727783
		},
		"Mississippi":{
			"contests":{
				"presidential":{
					"winners":1,
					"candidates":[
						"Biden",
						"Trump"
					],
					"results":[539398,756764],
					"ballots_cast":1313759,
					"state_id":28,
					"margin":-0.1676997165
				}
			},
			"round_sizes_Minerva_EoR":[259,518],
			"round_sizes_Minerva_EoR_scaled":[263,526],
			"round_sizes_factor":2,
			"distinct_Minerva_EoR":[263,526],
			"distinct_factor":2,
			"stop_prob_Minerva":0.9112494692,
			"stop_prob_EoR":0.9081523647
		},
		"Missouri":{
			"contests":{
				"presidential":{
					"winners":1,
					"candidates":[
						"Biden",
						"Trump"
					],
					"results":[1253014,1718736],
					"ballots_cast":3025962,
					"state_id":29,
					"margin":-0.1567164129
				}
			},
			"round_sizes_Minerva_EoR":[288,576],
			"round_sizes_Minerva_EoR_scaled":[294,587],
			"round_sizes_factor":2,
			"distinct_Minerva_EoR":[294,587],
			"distinct_factor":1.996598639,
			"stop_prob_Minerva":0.9063478351,
			"stop_prob_EoR":0.9061961427
		},
		"Montana":{
			"contests":{
				"presidential":{
					"winners":1,
					"candidates":[
						"Biden",
						"Trump"
					],
					"results":[244786,343602],
					"ballots_cast":603674,
					"state_id":30,
					"margin":-0.1679436018
				}
			},
			"round_sizes_Minerva_EoR":[257,509],
			"round_sizes_Minerva_EoR_scaled":[264,523],
			"round_sizes_factor":1.980544747,
			"distinct_Minerva_EoR":[264,523],
			"distinct_factor":1.981060606,
			"stop_prob_Minerva":0.9093265122,
			"stop_prob_EoR":0.9072377573
		},
		"Nebraska":{
			"contests":{
				"presidential":{
					"winners":1,
					"candidates":[
						"Biden",
						"Trump"
					],
					"results":[374583,556846],
					"ballots_cast":956383,
					"state_id":31,
					"margin":-0.1956810449
				}
			},
			"round_sizes_Minerva_EoR":[186,371],
			"round_sizes_Minerva_EoR_scaled":[191,381],
			"round_sizes_factor":1.994623656,
			"distinct_Minerva_EoR":[191,381],
			"distinct_factor":1.994764398,
			"stop_prob_Minerva":0.9028292005,
			"stop_prob_EoR":0.9032109871
		},
		"Nevada":{
			"contests":{
				"presidential":{
					"winners":1,
					"candidates":[
						"Biden",
						"Trump"
					],
					"results":[703486,669890],
					"ballots_cast":1405376,
					"state_id":32,
					"margin":0.0244623468
				}
			},
			"round_sizes_Minerva_EoR":[11562,23964],
			"round_sizes_Minerva_EoR_scaled":[11832,24523],
			"round_sizes_factor":2.07265179,
			"distinct_Minerva_EoR":[11783,24311],
			"distinct_factor":2.063226683,
			"stop_prob_Minerva":0.9001129586,
			"stop_prob_EoR":0.9009965495
		},
		"NewHampshire":{
			"contests":{
				"presidential":{
					"winners":1,
					"candidates":[
						"Biden",
						"Trump"
					],
					"results":[424921,365654],
					"ballots_cast":806182,
					"state_id":33,
					"margin":0.07496695443
				}
			},
			"round_sizes_Minerva_EoR":[1259,2553],
			"round_sizes_Minerva_EoR_scaled":[1284,2604],
			"round_sizes_factor":2.027799841,
			"distinct_Minerva_EoR":[1283,2600],
			"distinct_factor":2.02650039,
			"stop_prob_Minerva":0.9049813069,
			"stop_prob_EoR":0.9027719447
		},
		"NewJersey":{
			"contests":{
				"presidential":{
					"winners":1,
					"candidates":[
						"Biden",
						"Trump"
					],
					"results":[2608335,1883274],
					"ballots_cast":4549353,
					"state_id":34,
					"margin":0.1614256717
				}
			},
			"round_sizes_Minerva_EoR":[274,547],
			"round_sizes_Minerva_EoR_scaled":[278,555],
			"round_sizes_factor":1.996350365,
			"distinct_Minerva_EoR":[278,555],
			"distinct_factor":1.996402878,
			"stop_prob_Minerva":0.9028003197,
			"stop_prob_EoR":0.9051088623
		},
		"NewMexico":{
			"contests":{
				"presidential":{
					"winners":1,
					"candidates":[
						"Biden",
						"Trump"
					],
					"results":[501614,401894],
					"ballots_cast":923965,
					"state_id":35,
					"margin":0.110369803
				}
			},
			"round_sizes_Minerva_EoR":[586,1185],
			"round_sizes_Minerva_EoR_scaled":[600,1212],
			"round_sizes_factor":2.0221843,
			"distinct_Minerva_EoR":[600,1212],
			"distinct_factor":2.02,
			"stop_prob_Minerva":0.9058492516,
			"stop_prob_EoR":0.9046281277
		},
		"NewYork":{
			"contests":{
				"presidential":{
					"winners":1,
					"candidates":[
						"Biden",
						"Trump"
					],
					"results":[5230985,3244798],
					"ballots_cast":8661735,
					"state_id":36,
					"margin":0.2343366979
				}
			},
			"round_sizes_Minerva_EoR":[135,254],
			"round_sizes_Minerva_EoR_scaled":[138,260],
			"round_sizes_factor":1.881481481,
			"distinct_Minerva_EoR":[138,260],
			"distinct_factor":1.884057971,
			"stop_prob_Minerva":0.9160327328,
			"stop_prob_EoR":0.9067722558
		},
		"NorthCarolina":{
			"contests":{
				"presidential":{
					"winners":1,
					"candidates":[
						"Biden",
						"Trump"
					],
					"results":[2684292,2758773],
					"ballots_cast":5524802,
					"state_id":37,
					"margin":-0.01368365066
				}
			},
			"round_sizes_Minerva_EoR":[36875,76250],
			"round_sizes_Minerva_EoR_scaled":[37429,77396],
			"round_sizes_factor":2.06779661,
			"distinct_Minerva_EoR":[37303,76857],
			"distinct_factor":2.060343672,
			"stop_prob_Minerva":0.9004657591,
			"stop_prob_EoR":0.9003357011
		},
		"NorthDakota":{
			"contests":{
				"presidential":{
					"winners":1,
					"candidates":[
						"Biden",
						"Trump"
					],
					"results":[114902,235595],
					"ballots_cast":361819,
					"state_id":38,
					"margin":-0.3443481685
				}
			},
			"round_sizes_Minerva_EoR":[62,113],
			"round_sizes_Minerva_EoR_scaled":[65,117],
			"round_sizes_factor":1.822580645,
			"distinct_Minerva_EoR":[65,117],
			"distinct_factor":1.8,
			"stop_prob_Minerva":0.9174180388,
			"stop_prob_EoR":0.9009661004
		},
		"Ohio":{
			"contests":{
				"presidential":{
					"winners":1,
					"candidates":[
						"Biden",
						"Trump"
					],
					"results":[2679165,3154834],
					"ballots_cast":5922202,
					"state_id":39,
					"margin":-0.08153395295
				}
			},
			"round_sizes_Minerva_EoR":[1063,2148],
			"round_sizes_Minerva_EoR_scaled":[1080,2181],
			"round_sizes_factor":2.020696143,
			"distinct_Minerva_EoR":[1080,2181],
			"distinct_factor":2.019444444,
			"stop_prob_Minerva":0.9053426873,
			"stop_prob_EoR":0.9034509949
		},
		"Oklahoma":{
			"contests":{
				"presidential":{
					"winners":1,
					"candidates":[
						"Biden",
						"Trump"
					],
					"results":[503890,1020280],
					"ballots_cast":1560699,
					"state_id":40,
					"margin":-0.3388007899
				}
			},
			"round_sizes_Minerva_EoR":[64,122],
			"round_sizes_Minerva_EoR_scaled":[66,125],
			"round_sizes_factor":1.90625,
			"distinct_Minerva_EoR":[66,125],
			"distinct_factor":1.893939394,
			"stop_prob_Minerva":0.9202810738,
			"stop_prob_EoR":0.9147866745
		},
		"Oregon":{
			"contests":{
				"presidential":{
					"winners":1,
					"candidates":[
						"Biden",
						"Trump"
					],
					"results":[1340383,958448],
					"ballots_cast":2374321,
					"state_id":41,
					"margin":0.1661431397
				}
			},
			"round_sizes_Minerva_EoR":[259,517],
			"round_sizes_Minerva_EoR_scaled":[268,534],
			"round_sizes_factor":1.996138996,
			"distinct_Minerva_EoR":[268,534],
			"distinct_factor":1.992537313,
			"stop_prob_Minerva":0.9070745111,
			"stop_prob_EoR":0.908508478
		},
		"Pennsylvania":{
			"contests":{
				"presidential":{
					"winners":1,
					"candidates":[
						"Biden",
						"Trump"
					],
					"results":[3458229,3377674],
					"ballots_cast":6915283,
					"state_id":42,
					"margin":0.01178410519
				}
			},
			"round_sizes_Minerva_EoR":[49696,103144],
			"round_sizes_Minerva_EoR_scaled":[50274,104342],
			"round_sizes_factor":2.075499034,
			"distinct_Minerva_EoR":[50092,103559],
			"distinct_factor":2.067376028,
			"stop_prob_Minerva":0.9007453624,
			"stop_prob_EoR":0.9004922533
		},
		"RhodeIsland":{
			"contests":{
				"presidential":{
					"winners":1,
					"candidates":[
						"Biden",
						"Trump"
					],
					"results":[307486,199922],
					"ballots_cast":516990,
					"state_id":44,
					"margin":0.2119871977
				}
			},
			"round_sizes_Minerva_EoR":[160,313],
			"round_sizes_Minerva_EoR_scaled":[164,319],
			"round_sizes_factor":1.95625,
			"distinct_Minerva_EoR":[164,319],
			"distinct_factor":1.945121951,
			"stop_prob_Minerva":0.9137707277,
			"stop_prob_EoR":0.9015334243
		},
		"SouthCarolina":{
			"contests":{
				"presidential":{
					"winners":1,
					"candidates":[
						"Biden",
						"Trump"
					],
					"results":[1091541,1385103],
					"ballots_cast":2514096,
					"state_id":45,
					"margin":-0.118532175
				}
			},
			"round_sizes_Minerva_EoR":[508,1027],
			"round_sizes_Minerva_EoR_scaled":[516,1043],
			"round_sizes_factor":2.021653543,
			"distinct_Minerva_EoR":[516,1043],
			"distinct_factor":2.021317829,
			"stop_prob_Minerva":0.9039340448,
			"stop_prob_EoR":0.9050153512
		},
		"SouthDakota":{
			"contests":{
				"presidential":{
					"winners":1,
					"candidates":[
						"Biden",
						"Trump"
					],
					"results":[150471,261043],
					"ballots_cast":422609,
					"state_id":46,
					"margin":-0.2686955972
				}
			},
			"round_sizes_Minerva_EoR":[103,186],
			"round_sizes_Minerva_EoR_scaled":[106,192],
			"round_sizes_factor":1.805825243,
			"distinct_Minerva_EoR":[106,192],
			"distinct_factor":1.811320755,
			"stop_prob_Minerva":0.9179800934,
			"stop_prob_EoR":0.9011881922
		},
		"Tennessee":{
			"contests":{
				"presidential":{
					"winners":1,
					"candidates":[
						"Biden",
						"Trump"
					],
					"results":[1143711,1852475],
					"ballots_cast":3053851,
					"state_id":47,
					"margin":-0.2365554074
				}
			},
			"round_sizes_Minerva_EoR":[133,254],
			"round_sizes_Minerva_EoR_scaled":[136,259],
			"round_sizes_factor":1.909774436,
			"distinct_Minerva_EoR":[136,259],
			"distinct_factor":1.904411765,
			"stop_prob_Minerva":0.9153563078,
			"stop_prob_EoR":0.9127336181
		},
		"Texas":{
			"contests":{
				"presidential":{
					"winners":1,
					"candidates":[
						"Biden",
						"Trump"
					],
					"results":[5259126,5890347],
					"ballots_cast":11315056,
					"state_id":48,
					"margin":-0.05661442474
				}
			},
			"round_sizes_Minerva_EoR":[2188,4453],
			"round_sizes_Minerva_EoR_scaled":[2221,4520],
			"round_sizes_factor":2.035191956,
			"distinct_Minerva_EoR":[2221,4520],
			"distinct_factor":2.035119316,
			"stop_prob_Minerva":0.9037468409,
			"stop_prob_EoR":0.9018592831
		},
		"Utah":{
			"contests":{
				"presidential":{
					"winners":1,
					"candidates":[
						"Biden",
						"Trump"
					],
					"results":[560282,865140],
					"ballots_cast":1488289,
					"state_id":49,
					"margin":-0.2138721024
				}
			},
			"round_sizes_Minerva_EoR":[158,313],
			"round_sizes_Minerva_EoR_scaled":[165,327],
			"round_sizes_factor":1.981012658,
			"distinct_Minerva_EoR":[165,327],
			"distinct_factor":1.981818182,
			"stop_prob_Minerva":0.9135955448,
			"stop_prob_EoR":0.9073586322
		},
		"Vermont":{
			"contests":{
				"presidential":{
					"winners":1,
					"candidates":[
						"Biden",
						"Trump"
					],
					"results":[242820,112704],
					"ballots_cast":370968,
					"state_id":50,
					"margin":0.3659837311
				}
			},
			"round_sizes_Minerva_EoR":[55,104],
			"round_sizes_Minerva_EoR_scaled":[58,109],
			"round_sizes_factor":1.890909091,
			"distinct_Minerva_EoR":[58,109],
			"distinct_factor":1.879310345,
			"stop_prob_Minerva":0.9266460889,
			"stop_prob_EoR":0.9141157217
		},
		"Virginia":{
			"contests":{
				"presidential":{
					"winners":1,
					"candidates":[
						"Biden",
						"Trump"
					],
					"results":[2413568,1962430],
					"ballots_cast":4460524,
					"state_id":51,
					"margin":0.10309374
				}
			},
			"round_sizes_Minerva_EoR":[664,1342],
			"round_sizes_Minerva_EoR_scaled":[677,1368],
			"round_sizes_factor":2.021084337,
			"distinct_Minerva_EoR":[677,1368],
			"distinct_factor":2.020679468,
			"stop_prob_Minerva":0.9039529601,
			"stop_prob_EoR":0.9030146303
		},
		"Washington":{
			"contests":{
				"presidential":{
					"winners":1,
					"candidates":[
						"Biden",
						"Trump"
					],
					"results":[2369612,1584651],
					"ballots_cast":4087631,
					"state_id":53,
					"margin":0.1985100637
				}
			},
			"round_sizes_Minerva_EoR":[186,369],
			"round_sizes_Minerva_EoR_scaled":[193,382],
			"round_sizes_factor":1.983870968,
			"distinct_Minerva_EoR":[193,382],
			"distinct_factor":1.979274611,
			"stop_prob_Minerva":0.9094660291,
			"stop_prob_EoR":0.9096574692
		},
		"WestVirginia":{
			"contests":{
				"presidential":{
					"winners":1,
					"candidates":[
						"Biden",
						"Trump"
					],
					"results":[235984,545382],
					"ballots_cast":794652,
					"state_id":54,
					"margin":-0.3959706463
				}
			},
			"round_sizes_Minerva_EoR":[49,88],
			"round_sizes_Minerva_EoR_scaled":[50,90],
			"round_sizes_factor":1.795918367,
			"distinct_Minerva_EoR":[50,90],
			"distinct_factor":1.8,
			"stop_prob_Minerva":0.9256541574,
			"stop_prob_EoR":0.9136556257
		},
		"Wisconsin":{
			"contests":{
				"presidential":{
					"winners":1,
					"candidates":[
						"Biden",
						"Trump"
					],
					"results":[1630866,1610184],
					"ballots_cast":3298041,
					"state_id":55,
					"margin":0.006381265331
				}
			},
			"round_sizes_Minerva_EoR":[168867,351081],
			"round_sizes_Minerva_EoR_scaled":[171837,357255],
			"round_sizes_factor":2.079038533,
			"distinct_Minerva_EoR":[167438,338586],
			"distinct_factor":2.022157455,
			"stop_prob_EoR":0.8994094228
		},
		"Wyoming":{
			"contests":{
				"presidential":{
					"winners":1,
					"candidates":[
						"Biden",
						"Trump"
					],
					"results":[73491,193559],
					"ballots_cast":278503,
					"state_id":56,
					"margin":-0.4496086875
				}
			},
			"round_sizes_Minerva_EoR":[35,64],
			"round_sizes_Minerva_EoR_scaled":[37,67],
			"round_sizes_factor":1.828571429,
			"distinct_Minerva_EoR":[37,67],
			"distinct_factor":1.810810811,
			"stop_prob_Minerva":0.9249481791,
			"stop_prob_EoR":0.9119697339
		}
	}
}
